{"index.md":"CtYHihRH","技术的小记_atom 改装指南_index.md":"ClgLPoOx","技术的小记_extjs 自定义 datetimefield 控件_index.md":"j6kYQzG7","技术的小记_google 地图 tms 服务参数解析_index.md":"B5ouIGJR","技术的小记_index.md":"CmADz6vH","技术的小记_javascript 变量类型判断_index.md":"SrvzU2-w","技术的小记_photoshop 基础--如何抠图_index.md":"npgIe7eC","技术的小记_web 应用榨干 cpu 性能的正确姿势_index.md":"CH_sEb5Z","技术的小记_什么是原型链_index.md":"BQ7wIdNl","技术的小记_如何为 vue 组件提供 slots 静态类型检查_index.md":"5GN7ISnq","技术的小记_如何在 web 应用中使用 gdal （一）_index.md":"vYY8Xxl6","技术的小记_如何在 web 应用中使用 gdal （二）_index.md":"DwnwhjR-","技术的小记_如何设计一个 brainfuck 解释器_index.md":"BXr1M2AF","技术的小记_如何设计一个易用的tag组件_index.md":"4yzFlpgm","技术的小记_脚本化css_index.md":"Dk5UwX5V","派的玩耍小记_c 的 main 函数_index.md":"Cvl6I7b9","派的玩耍小记_gcc 的编译过程_index.md":"fSrtZeAX","派的玩耍小记_index.md":"Ds04Hwem","派的玩耍小记_orangepi lite 2 刷 ubuntu 18.04.4 方法_index.md":"DhjeTiKP","派的玩耍小记_新到的玩具_index.md":"D8zvyEDL","派的玩耍小记_驱动步进电机_index.md":"BwRXxBZs","生活咏叹调_index.md":"YPrzBUPT","生活咏叹调_两个和尚的故事_index.md":"DZsqYJys","生活咏叹调_我居然想变老_index.md":"z8KqTLdD","生活咏叹调_生命_index.md":"RA74noQl","生活咏叹调_生活宝鉴_index.md":"BtZpeLmp","生活咏叹调_顽强的绿萝_index.md":"Dg5dukwC"}
